LICENSE
MANIFEST.in
README.rst
pyproject.toml
setup.py
src/qtape/ctape.cpp
src/qtape/ctape.h
src/qtape/qtape.pxd
src/qtape/qtape.pyx
src/qtape.egg-info/PKG-INFO
src/qtape.egg-info/SOURCES.txt
src/qtape.egg-info/dependency_links.txt
src/qtape.egg-info/requires.txt
src/qtape.egg-info/top_level.txt