Metadata-Version: 2.1
Name: qtape
Version: 0.0.1
Summary: A python package for (quantum) time adaptive phase estimation
Author-email: Brennan de Neeve <brennan.mn@proton.me>
License-File: LICENSE
Requires-Dist: numpy
